flavortext/__init__.py
flavortext/flavortext.py
flavortext-1.1.0.dist-info/LICENSE
flavortext-1.1.0.dist-info/METADATA
flavortext-1.1.0.dist-info/WHEEL
flavortext-1.1.0.dist-info/top_level.txt
flavortext-1.1.0.dist-info/RECORD
