Metadata-Version: 2.1
Name: flavortext
Version: 1.1.0
Summary: You cant spell flavortext without vortex
Home-page: https://github.com/TheMingus/flavortext.py
Author: TheMingus
License: UNKNOWN
Project-URL: Bug Tracker, https://github.com/TheMingus/flavortext.py/issues
Platform: UNKNOWN
Classifier: Programming Language :: Python :: 3
Classifier: License :: OSI Approved :: MIT License
Classifier: Operating System :: OS Independent
Requires-Python: >=3.6
License-File: LICENSE
